ansible_parallel.py
ansible_parallel-2023.7.26.dist-info/LICENSE
ansible_parallel-2023.7.26.dist-info/METADATA
ansible_parallel-2023.7.26.dist-info/WHEEL
ansible_parallel-2023.7.26.dist-info/entry_points.txt
ansible_parallel-2023.7.26.dist-info/top_level.txt
ansible_parallel-2023.7.26.dist-info/RECORD
