Metadata-Version: 2.1
Name: ansible-parallel
Version: 2023.7.26
Summary: Run ansible playbooks in parallel.
Author-email: Julien Palard <julien@palard.fr>
License: MIT License
Project-URL: Homepage, https://git.afpy.org/mdk/ansible-parallel
Classifier: Development Status :: 5 - Production/Stable
Classifier: Intended Audience :: System Administrators
Classifier: License :: OSI Approved :: MIT License
Classifier: Natural Language :: English
Classifier: Programming Language :: Python :: 3
Requires-Python: >=3.7
License-File: LICENSE
